LICENSE
README.md
setup.cfg
setup.py
skm_pyutils/__init__.py
skm_pyutils/array.py
skm_pyutils/config.py
skm_pyutils/log.py
skm_pyutils/merge.py
skm_pyutils/path.py
skm_pyutils/pdf.py
skm_pyutils/plot.py
skm_pyutils/print.py
skm_pyutils/profile.py
skm_pyutils/save.py
skm_pyutils/stats.py
skm_pyutils/table.py
skm_pyutils.egg-info/PKG-INFO
skm_pyutils.egg-info/SOURCES.txt
skm_pyutils.egg-info/dependency_links.txt
skm_pyutils.egg-info/entry_points.txt
skm_pyutils.egg-info/requires.txt
skm_pyutils.egg-info/top_level.txt