Metadata-Version: 2.1
Name: skm-pyutils
Version: 1.0.0
Summary: skm_pyutils: Python Utilities
Home-page: https://github.com/seankmartin/PythonUtils
Download-URL: https://github.com/seankmartin/PythonUtils/archive/0.1.8.tar.gz
Author: Sean Martin
Author-email: martins7@tcd.ie
Maintainer: Sean Martin
Maintainer-email: martins7@tcd.ie
Classifier: Intended Audience :: Science/Research
Classifier: Topic :: Scientific/Engineering :: Mathematics
Classifier: Programming Language :: Python :: 3.6
Classifier: Programming Language :: Python :: 3.7
Classifier: Programming Language :: Python :: 3.8
Classifier: Operating System :: POSIX
Classifier: Operating System :: Unix
Classifier: Operating System :: MacOS
Classifier: Operating System :: Microsoft :: Windows
Classifier: License :: OSI Approved :: GNU General Public License v3 (GPLv3)
License-File: LICENSE
